{"sessions": {"single": {"bmp": "{\"reading000\":{\"T\":29.44,\"P\":909.39},\"reading000\":{\"T\":29.41,\"P\":909.27},\"reading000\":{\"T\":29.42,\"P\":909.25},\"reading000\":{\"T\":29.41,\"P\":909.28},\"reading000\":{\"T\":29.41,\"P\":909.24},\"reading000\":{\"T\":29.42,\"P\":909.29},\"reading000\":{\"T\":29.41,\"P\":909.32},\"reading000\":{\"T\":29.43,\"P\":909.29},\"reading000\":{\"T\":29.43,\"P\":909.29},\"reading000\":{\"T\":29.43,\"P\":909.28},\"reading001\":{\"T\":29.42,\"P\":909.14},\"reading001\":{\"T\":29.44,\"P\":909.14},\"reading001\":{\"T\":29.43,\"P\":909.16},\"reading001\":{\"T\":29.44,\"P\":909.06},\"reading001\":{\"T\":29.45,\"P\":909.18},\"reading001\":{\"T\":29.45,\"P\":909.05},\"reading001\":{\"T\":29.45,\"P\":908.96},\"reading001\":{\"T\":29.46,\"P\":908.99},\"reading001\":{\"T\":29.47,\"P\":908.95},\"reading001\":{\"T\":29.47,\"P\":908.89},\"reading002\":{\"T\":29.48,\"P\":908.94},\"reading002\":{\"T\":29.47,\"P\":908.88},\"reading002\":{\"T\":29.48,\"P\":908.82},\"reading002\":{\"T\":29.47,\"P\":908.75},\"reading002\":{\"T\":29.48,\"P\":908.78},\"reading002\":{\"T\":29.49,\"P\":908.80},\"reading002\":{\"T\":29.50,\"P\":908.73},\"reading002\":{\"T\":29.49,\"P\":908.68},\"reading002\":{\"T\":29.50,\"P\":908.69},\"reading002\":{\"T\":29.50,\"P\":908.65},\"reading003\":{\"T\":29.50,\"P\":908.57},\"reading003\":{\"T\":29.51,\"P\":908.61},\"reading003\":{\"T\":29.52,\"P\":908.65},\"reading003\":{\"T\":29.51,\"P\":908.80},\"reading003\":{\"T\":29.51,\"P\":908.72},\"reading003\":{\"T\":29.52,\"P\":908.64},\"reading003\":{\"T\":29.51,\"P\":908.57},\"reading003\":{\"T\":29.50,\"P\":908.56},\"reading003\":{\"T\":29.51,\"P\":908.66},\"reading003\":{\"T\":29.51,\"P\":908.58},\"reading004\":{\"T\":29.52,\"P\":908.62},\"reading004\":{\"T\":29.53,\"P\":908.70},\"reading004\":{\"T\":29.51,\"P\":908.66},\"reading004\":{\"T\":29.50,\"P\":908.62},\"reading004\":{\"T\":29.51,\"P\":908.65},\"reading004\":{\"T\":29.51,\"P\":908.66},\"reading004\":{\"T\":29.52,\"P\":908.69},\"reading004\":{\"T\":29.52,\"P\":908.67},\"reading004\":{\"T\":29.52,\"P\":908.66},\"reading004\":{\"T\":29.54,\"P\":908.72},\"reading005\":{\"T\":29.53,\"P\":908.67},\"reading005\":{\"T\":29.55,\"P\":908.75},\"reading005\":{\"T\":29.54,\"P\":908.70},\"reading005\":{\"T\":29.55,\"P\":908.68},\"reading005\":{\"T\":29.55,\"P\":908.66},\"reading005\":{\"T\":29.57,\"P\":908.69},\"reading005\":{\"T\":30.60,\"P\":912.40},\"reading005\":{\"T\":30.60,\"P\":912.40}}", "mpu": "{\"reading000\":{\"ax\":-600,\"ay\":707,\"az\":1795,\"gx\":-16,\"gy\":207,\"gz\":-23},\"reading000\":{\"ax\":-606,\"ay\":714,\"az\":1789,\"gx\":-23,\"gy\":208,\"gz\":-22},\"reading000\":{\"ax\":-597,\"ay\":704,\"az\":1797,\"gx\":-22,\"gy\":212,\"gz\":-20},\"reading000\":{\"ax\":-598,\"ay\":707,\"az\":1778,\"gx\":-17,\"gy\":212,\"gz\":-25},\"reading000\":{\"ax\":-585,\"ay\":698,\"az\":1791,\"gx\":-23,\"gy\":216,\"gz\":-22},\"reading000\":{\"ax\":-599,\"ay\":706,\"az\":1786,\"gx\":-20,\"gy\":210,\"gz\":-20},\"reading000\":{\"ax\":-606,\"ay\":707,\"az\":1799,\"gx\":-21,\"gy\":210,\"gz\":-19},\"reading000\":{\"ax\":-594,\"ay\":704,\"az\":1788,\"gx\":-15,\"gy\":212,\"gz\":-21},\"reading000\":{\"ax\":-596,\"ay\":700,\"az\":1797,\"gx\":-20,\"gy\":207,\"gz\":-22},\"reading000\":{\"ax\":-195,\"ay\":2084,\"az\":-288,\"gx\":-47,\"gy\":246,\"gz\":93},\"reading001\":{\"ax\":-915,\"ay\":528,\"az\":1766,\"gx\":60,\"gy\":191,\"gz\":32},\"reading001\":{\"ax\":-461,\"ay\":1820,\"az\":-229,\"gx\":-2880,\"gy\":-441,\"gz\":166},\"reading001\":{\"ax\":-966,\"ay\":190,\"az\":1746,\"gx\":-16,\"gy\":208,\"gz\":-13},\"reading001\":{\"ax\":-691,\"ay\":1831,\"az\":41,\"gx\":1829,\"gy\":702,\"gz\":35},\"reading001\":{\"ax\":-1043,\"ay\":401,\"az\":1954,\"gx\":-288,\"gy\":296,\"gz\":-129},\"reading001\":{\"ax\":-683,\"ay\":1958,\"az\":210,\"gx\":-570,\"gy\":19,\"gz\":-28},\"reading001\":{\"ax\":-1045,\"ay\":352,\"az\":1791,\"gx\":-186,\"gy\":252,\"gz\":-52},\"reading001\":{\"ax\":-722,\"ay\":1910,\"az\":-74,\"gx\":-748,\"gy\":-152,\"gz\":200},\"reading001\":{\"ax\":-727,\"ay\":849,\"az\":1706,\"gx\":1261,\"gy\":-158,\"gz\":251},\"reading001\":{\"ax\":-636,\"ay\":1394,\"az\":1374,\"gx\":-1390,\"gy\":93,\"gz\":-192},\"reading002\":{\"ax\":-742,\"ay\":1060,\"az\":1477,\"gx\":1429,\"gy\":170,\"gz\":526},\"reading002\":{\"ax\":-701,\"ay\":1262,\"az\":1387,\"gx\":-1679,\"gy\":-155,\"gz\":-361},\"reading002\":{\"ax\":-887,\"ay\":907,\"az\":1561,\"gx\":1276,\"gy\":-331,\"gz\":567},\"reading002\":{\"ax\":-837,\"ay\":737,\"az\":1700,\"gx\":-2010,\"gy\":870,\"gz\":-665},\"reading002\":{\"ax\":-1298,\"ay\":334,\"az\":1688,\"gx\":504,\"gy\":-73,\"gz\":325},\"reading002\":{\"ax\":-938,\"ay\":559,\"az\":1791,\"gx\":-986,\"gy\":412,\"gz\":-373},\"reading002\":{\"ax\":-1232,\"ay\":-52,\"az\":1641,\"gx\":627,\"gy\":101,\"gz\":283},\"reading002\":{\"ax\":-678,\"ay\":1495,\"az\":1039,\"gx\":-1949,\"gy\":-385,\"gz\":-569},\"reading002\":{\"ax\":-997,\"ay\":716,\"az\":1513,\"gx\":1913,\"gy\":109,\"gz\":946},\"reading002\":{\"ax\":-1276,\"ay\":644,\"az\":1959,\"gx\":-977,\"gy\":1070,\"gz\":-948},\"reading003\":{\"ax\":-794,\"ay\":1511,\"az\":946,\"gx\":1930,\"gy\":716,\"gz\":426},\"reading003\":{\"ax\":-1161,\"ay\":777,\"az\":1628,\"gx\":-811,\"gy\":967,\"gz\":-816},\"reading003\":{\"ax\":-833,\"ay\":1785,\"az\":341,\"gx\":1133,\"gy\":595,\"gz\":110},\"reading003\":{\"ax\":-1364,\"ay\":667,\"az\":1674,\"gx\":-310,\"gy\":357,\"gz\":-355},\"reading003\":{\"ax\":-759,\"ay\":1908,\"az\":-73,\"gx\":-1059,\"gy\":-329,\"gz\":-112},\"reading003\":{\"ax\":-929,\"ay\":911,\"az\":1621,\"gx\":786,\"gy\":-46,\"gz\":420},\"reading003\":{\"ax\":-1216,\"ay\":616,\"az\":1629,\"gx\":-260,\"gy\":888,\"gz\":-404},\"reading003\":{\"ax\":-949,\"ay\":1511,\"az\":772,\"gx\":-1143,\"gy\":-372,\"gz\":-297},\"reading003\":{\"ax\":-899,\"ay\":981,\"az\":1401,\"gx\":2739,\"gy\":1232,\"gz\":921},\"reading003\":{\"ax\":-1179,\"ay\":453,\"az\":1797,\"gx\":296,\"gy\":49,\"gz\":276},\"reading004\":{\"ax\":-555,\"ay\":1715,\"az\":523,\"gx\":-2465,\"gy\":-585,\"gz\":-119},\"reading004\":{\"ax\":-694,\"ay\":1725,\"az\":754,\"gx\":1227,\"gy\":663,\"gz\":48},\"reading004\":{\"ax\":-600,\"ay\":670,\"az\":1667,\"gx\":979,\"gy\":86,\"gz\":476},\"reading004\":{\"ax\":-1306,\"ay\":546,\"az\":1903,\"gx\":491,\"gy\":-297,\"gz\":300},\"reading004\":{\"ax\":-990,\"ay\":485,\"az\":1963,\"gx\":-1058,\"gy\":248,\"gz\":-525},\"reading004\":{\"ax\":-722,\"ay\":1338,\"az\":1461,\"gx\":-1765,\"gy\":-676,\"gz\":-404},\"reading004\":{\"ax\":-1206,\"ay\":277,\"az\":1770,\"gx\":2500,\"gy\":-392,\"gz\":1098},\"reading004\":{\"ax\":-723,\"ay\":916,\"az\":1681,\"gx\":-1915,\"gy\":827,\"gz\":-903},\"reading004\":{\"ax\":-824,\"ay\":1653,\"az\":709,\"gx\":1163,\"gy\":622,\"gz\":101},\"reading004\":{\"ax\":-1212,\"ay\":-159,\"az\":1909,\"gx\":668,\"gy\":-252,\"gz\":186},\"reading005\":{\"ax\":-173,\"ay\":771,\"az\":1711,\"gx\":-2607,\"gy\":-94,\"gz\":-540},\"reading005\":{\"ax\":-374,\"ay\":1461,\"az\":1192,\"gx\":1962,\"gy\":687,\"gz\":69},\"reading005\":{\"ax\":-1097,\"ay\":-82,\"az\":1845,\"gx\":-551,\"gy\":391,\"gz\":-247},\"reading005\":{\"ax\":-845,\"ay\":1659,\"az\":692,\"gx\":-614,\"gy\":-171,\"gz\":-83},\"reading005\":{\"ax\":-1233,\"ay\":214,\"az\":1868,\"gx\":1356,\"gy\":-102,\"gz\":648},\"reading005\":{\"ax\":-739,\"ay\":396,\"az\":886,\"gx\":-3293,\"gy\":2594,\"gz\":-349},\"reading005\":{\"ax\":-908,\"ay\":1655,\"az\":570,\"gx\":811,\"gy\":688,\"gz\":148}}"}}}